{"stats":{"minecraft:crafted":{"minecraft:crafting_table":1,"minecraft:oak_planks":16,"minecraft:stick":8},"minecraft:picked_up":{"minecraft:oak_log":4},"minecraft:mined":{"minecraft:short_grass":3,"minecraft:oak_log":4,"minecraft:oak_leaves":4},"minecraft:custom":{"minecraft:jump":63,"minecraft:time_since_rest":2050,"minecraft:damage_taken":30,"minecraft:leave_game":2,"minecraft:play_time":2050,"minecraft:sprint_one_cm":8400,"minecraft:time_since_death":2050,"minecraft:walk_one_cm":970,"minecraft:total_world_time":2050,"minecraft:fall_one_cm":2717,"minecraft:fly_one_cm":11038}},"DataVersion":3953}